{"data": [
  {"id": 79, "value": "tEt9rkjY"},
  {"id": 288, "value": "DghnU3AW"},
  {"id": 652, "value": "FIaLWWjm"},
  {"id": 805, "value": "C6DrpIi5"},
  {"id": 18, "value": "FtliBKSF"},
  {"id": 785, "value": "6QVqbFsM"},
  {"id": 191, "value": "iRacpZUb"},
  {"id": 756, "value": "R2G7jasq"},
  {"id": 805, "value": "97I4yeu4"},
  {"id": 979, "value": "Srid4kha"},
  {"id": 240, "value": "8TFImkhG"},
  {"id": 560, "value": "HYAChVOl"},
  {"id": 21, "value": "OTCagf6r"},
  {"id": 304, "value": "Wi4Vmc8O"},
  {"id": 391, "value": "jS9unwKl"},
  {"id": 901, "value": "8E725xSU"},
  {"id": 222, "value": "YfmFRK1A"},
  {"id": 211, "value": "AqAHqEyE"},
  {"id": 641, "value": "dPJhi7oO"},
  {"id": 637, "value": "Ibs8AEM5"},
  {"id": 726, "value": "kX7RTO8r"},
  {"id": 247, "value": "uQr7O52q"},
  {"id": 890, "value": "7jvnQP6w"},
  {"id": 411, "value": "rYXMdY56"},
  {"id": 271, "value": "VkMaJZSS"},
  {"id": 415, "value": "OV0I8Hfi"},
  {"id": 249, "value": "T34hhjSR"},
  {"id": 878, "value": "VoCT4adX"},
  {"id": 820, "value": "NhzMO3I0"},
  {"id": 120, "value": "GLTY3ub4"},
  {"id": 754, "value": "TGBf7Gx3"},
  {"id": 212, "value": "SdrcT0ih"},
  {"id": 411, "value": "zX3HMRkh"},
  {"id": 333, "value": "ReXuL87v"},
  {"id": 46, "value": "v0cus3Cu"},
  {"id": 108, "value": "zX5nFHRn"},
  {"id": 940, "value": "h10kqagT"},
  {"id": 191, "value": "PS25s5iR"},
  {"id": 720, "value": "dNVIEVra"},
  {"id": 142, "value": "7x3Eymfh"},
  {"id": 561, "value": "FW7Pzo7a"},
  {"id": 790, "value": "z2b3VHb0"},
  {"id": 545, "value": "THQ5X5DB"},
  {"id": 746, "value": "fN5mzRQ4"},
  {"id": 213, "value": "gyZ6tLMB"},
  {"id": 518, "value": "cLvECs2R"},
  {"id": 411, "value": "b1LULypX"},
  {"id": 276, "value": "km79bB3b"},
  {"id": 491, "value": "RwV0C3Cx"},
  {"id": 136, "value": "mIuFIiMN"},
  {"id": 9999, "value": "END"}
]}
